{
    "name" : "test",
    "geometry" :
    {
        "name" :"HexaIso",
        "size" : 50.0
    },
    "layers" : 
    [
        {
            "content" : "tile",
            "z" : 1,
            "static" : true,
            "datas" : 
            [
                {
                    "img" :"media/img/ground.png",
                    "x" : 0,
                    "y" : 0,
                    "width" : 100,
                    "height" : 100
                }
            ]
        },
        {
            "content" : "sprite",
            "z" : 3,
            "datas" : 
            [
                {"x" : 44, "y" : 49, "img" : "media/img/tree/bush4.png"},
                {"x" : 7, "y" : 91, "img" : "media/img/tree/tree3.png"},
                {"x" : 65, "y" : 58, "img" : "media/img/tree/tree3.png"},
                {"x" : 25, "y" : 17, "img" : "media/img/tree/tree2.png"},
                {"x" : 3, "y" : 85, "img" : "media/img/tree/bush1.png"},
                {"x" : 6, "y" : 4, "img" : "media/img/tree/bush1.png"},
                {"x" : 52, "y" : 61, "img" : "media/img/tree/tree1_g_dead.png"},
                {"x" : 34, "y" : 20, "img" : "media/img/tree/bush1_g.png"},
                {"x" : 0, "y" : 82, "img" : "media/img/tree/trunk.png"},
                {"x" : 62, "y" : 64, "img" : "media/img/tree/bush1_g_dead.png"},
                {"x" : 8, "y" : 60, "img" : "media/img/tree/bush1_g.png"},
                {"x" : 86, "y" : 93, "img" : "media/img/tree/bush2.png"},
                {"x" : 61, "y" : 53, "img" : "media/img/tree/tree2.png"},
                {"x" : 90, "y" : 10, "img" : "media/img/tree/trunk2.png"},
                {"x" : 75, "y" : 39, "img" : "media/img/tree/bush1_g_dead.png"},
                {"x" : 59, "y" : 77, "img" : "media/img/tree/tree1.png"},
                {"x" : 62, "y" : 2, "img" : "media/img/tree/tree3_dead.png"},
                {"x" : 38, "y" : 17, "img" : "media/img/tree/tree1_dead.png"},
                {"x" : 87, "y" : 4, "img" : "media/img/tree/bush2.png"},
                {"x" : 64, "y" : 2, "img" : "media/img/tree/tree2.png"},
                {"x" : 95, "y" : 3, "img" : "media/img/tree/tree2.png"},
                {"x" : 26, "y" : 18, "img" : "media/img/tree/trunk2.png"},
                {"x" : 7, "y" : 51, "img" : "media/img/tree/bush2_g.png"},
                {"x" : 44, "y" : 9, "img" : "media/img/tree/trunk.png"},
                {"x" : 66, "y" : 59, "img" : "media/img/tree/tree2.png"},
                {"x" : 20, "y" : 8, "img" : "media/img/tree/bush2.png"},
                {"x" : 90, "y" : 63, "img" : "media/img/tree/bush1_g.png"},
                {"x" : 88, "y" : 30, "img" : "media/img/tree/bush2_g.png"},
                {"x" : 74, "y" : 63, "img" : "media/img/tree/bush4.png"},
                {"x" : 56, "y" : 75, "img" : "media/img/tree/tree2.png"},
                {"x" : 48, "y" : 93, "img" : "media/img/tree/tree1_dead.png"},
                {"x" : 17, "y" : 59, "img" : "media/img/tree/bush2.png"},
                {"x" : 81, "y" : 97, "img" : "media/img/tree/tree2_g.png"},
                {"x" : 47, "y" : 21, "img" : "media/img/tree/tree3_dead.png"},
                {"x" : 67, "y" : 39, "img" : "media/img/tree/bush1.png"},
                {"x" : 71, "y" : 77, "img" : "media/img/tree/tree3.png"},
                {"x" : 31, "y" : 18, "img" : "media/img/tree/bush2_g.png"},
                {"x" : 7, "y" : 62, "img" : "media/img/tree/tree1.png"},
                {"x" : 94, "y" : 61, "img" : "media/img/tree/trunk.png"},
                {"x" : 96, "y" : 48, "img" : "media/img/tree/trunk2.png"},
                {"x" : 23, "y" : 5, "img" : "media/img/tree/bush1_g_dead.png"},
                {"x" : 1, "y" : 0, "img" : "media/img/tree/bush1_g_dead.png"},
                {"x" : 41, "y" : 36, "img" : "media/img/tree/tree2_g.png"},
                {"x" : 68, "y" : 34, "img" : "media/img/tree/trunk2.png"},
                {"x" : 71, "y" : 2, "img" : "media/img/tree/bush1_g.png"},
                {"x" : 47, "y" : 19, "img" : "media/img/tree/tree3_dead.png"},
                {"x" : 21, "y" : 92, "img" : "media/img/tree/bush2_g.png"},
                {"x" : 15, "y" : 84, "img" : "media/img/tree/tree2.png"},
                {"x" : 62, "y" : 28, "img" : "media/img/tree/bush3.png"},
                {"x" : 2, "y" : 69, "img" : "media/img/tree/bush1_g_dead.png"},
                {"x" : 72, "y" : 84, "img" : "media/img/tree/tree1.png"},
                {"x" : 97, "y" : 49, "img" : "media/img/tree/bush1_g_dead.png"},
                {"x" : 62, "y" : 73, "img" : "media/img/tree/bush1.png"},
                {"x" : 59, "y" : 47, "img" : "media/img/tree/trunk2.png"},
                {"x" : 79, "y" : 86, "img" : "media/img/tree/bush1_g_dead.png"},
                {"x" : 52, "y" : 0, "img" : "media/img/tree/bush1_g.png"},
                {"x" : 79, "y" : 13, "img" : "media/img/tree/tree2_g.png"},
                {"x" : 56, "y" : 97, "img" : "media/img/tree/tree1_g.png"},
                {"x" : 3, "y" : 43, "img" : "media/img/tree/trunk2.png"},
                {"x" : 84, "y" : 30, "img" : "media/img/tree/trunk2.png"},
                {"x" : 47, "y" : 89, "img" : "media/img/tree/bush1_g_dead.png"},
                {"x" : 96, "y" : 5, "img" : "media/img/tree/bush1_g.png"},
                {"x" : 90, "y" : 33, "img" : "media/img/tree/bush4.png"},
                {"x" : 89, "y" : 3, "img" : "media/img/tree/tree1.png"},
                {"x" : 52, "y" : 26, "img" : "media/img/tree/tree1_dead.png"},
                {"x" : 39, "y" : 20, "img" : "media/img/tree/trunk.png"},
                {"x" : 13, "y" : 71, "img" : "media/img/tree/bush1.png"},
                {"x" : 20, "y" : 9, "img" : "media/img/tree/tree1_g_dead.png"},
                {"x" : 50, "y" : 77, "img" : "media/img/tree/tree3_dead.png"},
                {"x" : 46, "y" : 43, "img" : "media/img/tree/tree1_dead.png"},
                {"x" : 67, "y" : 18, "img" : "media/img/tree/tree3_dead.png"},
                {"x" : 7, "y" : 5, "img" : "media/img/tree/bush1_g_dead.png"},
                {"x" : 10, "y" : 52, "img" : "media/img/tree/bush2.png"},
                {"x" : 10, "y" : 62, "img" : "media/img/tree/bush2_g.png"},
                {"x" : 72, "y" : 52, "img" : "media/img/tree/bush1.png"},
                {"x" : 48, "y" : 52, "img" : "media/img/tree/trunk.png"},
                {"x" : 36, "y" : 27, "img" : "media/img/tree/tree2.png"},
                {"x" : 77, "y" : 85, "img" : "media/img/tree/bush1_g_dead.png"},
                {"x" : 76, "y" : 41, "img" : "media/img/tree/bush1_g_dead.png"},
                {"x" : 26, "y" : 15, "img" : "media/img/tree/tree3.png"},
                {"x" : 3, "y" : 39, "img" : "media/img/tree/tree3_dead.png"},
                {"x" : 58, "y" : 49, "img" : "media/img/tree/bush4.png"},
                {"x" : 4, "y" : 44, "img" : "media/img/tree/tree2.png"},
                {"x" : 7, "y" : 84, "img" : "media/img/tree/tree1_dead.png"},
                {"x" : 83, "y" : 42, "img" : "media/img/tree/tree1_dead.png"},
                {"x" : 20, "y" : 28, "img" : "media/img/tree/bush1_g.png"},
                {"x" : 58, "y" : 61, "img" : "media/img/tree/tree1.png"},
                {"x" : 67, "y" : 72, "img" : "media/img/tree/bush2_g.png"},
                {"x" : 98, "y" : 58, "img" : "media/img/tree/bush2_g.png"},
                {"x" : 50, "y" : 76, "img" : "media/img/tree/bush2.png"},
                {"x" : 95, "y" : 91, "img" : "media/img/tree/bush1_g.png"},
                {"x" : 61, "y" : 84, "img" : "media/img/tree/bush1_g.png"},
                {"x" : 25, "y" : 67, "img" : "media/img/tree/bush1_g.png"},
                {"x" : 38, "y" : 21, "img" : "media/img/tree/bush2_g.png"},
                {"x" : 21, "y" : 78, "img" : "media/img/tree/trunk2.png"},
                {"x" : 76, "y" : 76, "img" : "media/img/tree/bush3.png"},
                {"x" : 5, "y" : 72, "img" : "media/img/tree/bush2.png"},
                {"x" : 83, "y" : 0, "img" : "media/img/tree/tree2.png"},
                {"x" : 48, "y" : 21, "img" : "media/img/tree/bush1.png"},
                {"x" : 76, "y" : 1, "img" : "media/img/tree/tree3.png"},
                {"x" : 4, "y" : 0, "img" : "media/img/tree/tree1.png"},
                {"x" : 12, "y" : 93, "img" : "media/img/tree/trunk.png"},
                {"x" : 6, "y" : 18, "img" : "media/img/tree/bush1.png"},
                {"x" : 54, "y" : 86, "img" : "media/img/tree/tree1_g.png"},
                {"x" : 74, "y" : 85, "img" : "media/img/tree/bush2_g.png"},
                {"x" : 20, "y" : 60, "img" : "media/img/tree/bush2_g.png"},
                {"x" : 76, "y" : 75, "img" : "media/img/tree/bush3.png"},
                {"x" : 98, "y" : 47, "img" : "media/img/tree/trunk.png"},
                {"x" : 77, "y" : 87, "img" : "media/img/tree/bush2.png"},
                {"x" : 93, "y" : 44, "img" : "media/img/tree/tree3.png"},
                {"x" : 81, "y" : 56, "img" : "media/img/tree/bush1_g.png"},
                {"x" : 15, "y" : 76, "img" : "media/img/tree/tree1_dead.png"},
                {"x" : 28, "y" : 28, "img" : "media/img/tree/tree1_g_dead.png"},
                {"x" : 77, "y" : 16, "img" : "media/img/tree/bush1_g.png"},
                {"x" : 98, "y" : 34, "img" : "media/img/tree/bush2.png"},
                {"x" : 4, "y" : 41, "img" : "media/img/tree/bush3.png"},
                {"x" : 2, "y" : 55, "img" : "media/img/tree/bush4.png"},
                {"x" : 78, "y" : 56, "img" : "media/img/tree/trunk.png"},
                {"x" : 29, "y" : 36, "img" : "media/img/tree/bush4.png"},
                {"x" : 83, "y" : 49, "img" : "media/img/tree/tree1_g.png"},
                {"x" : 98, "y" : 43, "img" : "media/img/tree/tree2_g.png"},
                {"x" : 64, "y" : 29, "img" : "media/img/tree/trunk2.png"},
                {"x" : 44, "y" : 75, "img" : "media/img/tree/tree1_g.png"},
                {"x" : 42, "y" : 54, "img" : "media/img/tree/bush1_g.png"},
                {"x" : 20, "y" : 55, "img" : "media/img/tree/bush2.png"},
                {"x" : 1, "y" : 73, "img" : "media/img/tree/tree3.png"},
                {"x" : 32, "y" : 69, "img" : "media/img/tree/tree3_dead.png"},
                {"x" : 32, "y" : 56, "img" : "media/img/tree/trunk2.png"},
                {"x" : 24, "y" : 42, "img" : "media/img/tree/bush1_g_dead.png"},
                {"x" : 51, "y" : 75, "img" : "media/img/tree/trunk2.png"},
                {"x" : 13, "y" : 29, "img" : "media/img/tree/bush1_g_dead.png"},
                {"x" : 14, "y" : 19, "img" : "media/img/tree/trunk.png"},
                {"x" : 92, "y" : 56, "img" : "media/img/tree/tree2.png"},
                {"x" : 23, "y" : 45, "img" : "media/img/tree/bush3.png"},
                {"x" : 21, "y" : 60, "img" : "media/img/tree/trunk.png"},
                {"x" : 13, "y" : 82, "img" : "media/img/tree/bush1_g.png"},
                {"x" : 21, "y" : 8, "img" : "media/img/tree/bush1.png"},
                {"x" : 17, "y" : 50, "img" : "media/img/tree/tree1_dead.png"},
                {"x" : 17, "y" : 82, "img" : "media/img/tree/tree3_dead.png"},
                {"x" : 3, "y" : 82, "img" : "media/img/tree/bush4.png"},
                {"x" : 18, "y" : 17, "img" : "media/img/tree/bush2.png"},
                {"x" : 40, "y" : 80, "img" : "media/img/tree/trunk.png"},
                {"x" : 79, "y" : 65, "img" : "media/img/tree/bush1_g.png"},
                {"x" : 58, "y" : 48, "img" : "media/img/tree/bush2_g.png"},
                {"x" : 67, "y" : 29, "img" : "media/img/tree/bush1_g.png"},
                {"x" : 97, "y" : 35, "img" : "media/img/tree/tree1_g_dead.png"},
                {"x" : 6, "y" : 16, "img" : "media/img/tree/bush1_g_dead.png"},
                {"x" : 98, "y" : 47, "img" : "media/img/tree/bush3.png"},
                {"x" : 20, "y" : 21, "img" : "media/img/tree/tree1_g.png"},
                {"x" : 94, "y" : 49, "img" : "media/img/tree/tree2_g.png"},
                {"x" : 39, "y" : 8, "img" : "media/img/tree/bush4.png"},
                {"x" : 10, "y" : 34, "img" : "media/img/tree/tree1.png"},
                {"x" : 86, "y" : 17, "img" : "media/img/tree/tree3.png"},
                {"x" : 60, "y" : 75, "img" : "media/img/tree/trunk2.png"},
                {"x" : 81, "y" : 35, "img" : "media/img/tree/tree1_g.png"},
                {"x" : 22, "y" : 88, "img" : "media/img/tree/tree2_g.png"},
                {"x" : 18, "y" : 63, "img" : "media/img/tree/tree1_g_dead.png"},
                {"x" : 58, "y" : 28, "img" : "media/img/tree/bush1.png"},
                {"x" : 12, "y" : 31, "img" : "media/img/tree/bush1_g_dead.png"},
                {"x" : 22, "y" : 4, "img" : "media/img/tree/tree2_g.png"},
                {"x" : 86, "y" : 53, "img" : "media/img/tree/tree1.png"},
                {"x" : 76, "y" : 51, "img" : "media/img/tree/trunk2.png"},
                {"x" : 73, "y" : 97, "img" : "media/img/tree/trunk.png"},
                {"x" : 28, "y" : 63, "img" : "media/img/tree/tree1_dead.png"},
                {"x" : 95, "y" : 97, "img" : "media/img/tree/trunk2.png"},
                {"x" : 91, "y" : 87, "img" : "media/img/tree/bush2.png"},
                {"x" : 9, "y" : 24, "img" : "media/img/tree/tree1_dead.png"},
                {"x" : 18, "y" : 35, "img" : "media/img/tree/bush3.png"},
                {"x" : 22, "y" : 30, "img" : "media/img/tree/bush2_g.png"},
                {"x" : 57, "y" : 22, "img" : "media/img/tree/tree3.png"},
                {"x" : 20, "y" : 15, "img" : "media/img/tree/bush1_g.png"},
                {"x" : 51, "y" : 31, "img" : "media/img/tree/tree2.png"},
                {"x" : 73, "y" : 26, "img" : "media/img/tree/tree3.png"},
                {"x" : 90, "y" : 58, "img" : "media/img/tree/tree3_dead.png"},
                {"x" : 91, "y" : 7, "img" : "media/img/tree/bush4.png"},
                {"x" : 52, "y" : 13, "img" : "media/img/tree/bush1_g_dead.png"},
                {"x" : 97, "y" : 77, "img" : "media/img/tree/tree3_dead.png"},
                {"x" : 75, "y" : 87, "img" : "media/img/tree/tree1_g_dead.png"},
                {"x" : 60, "y" : 11, "img" : "media/img/tree/tree2_g.png"},
                {"x" : 5, "y" : 18, "img" : "media/img/tree/trunk2.png"},
                {"x" : 27, "y" : 86, "img" : "media/img/tree/tree1.png"},
                {"x" : 17, "y" : 25, "img" : "media/img/tree/tree1_dead.png"},
                {"x" : 61, "y" : 1, "img" : "media/img/tree/trunk2.png"},
                {"x" : 51, "y" : 36, "img" : "media/img/tree/tree3.png"},
                {"x" : 89, "y" : 98, "img" : "media/img/tree/bush1.png"},
                {"x" : 41, "y" : 82, "img" : "media/img/tree/tree2.png"},
                {"x" : 91, "y" : 54, "img" : "media/img/tree/tree3_dead.png"},
                {"x" : 1, "y" : 74, "img" : "media/img/tree/bush4.png"},
                {"x" : 17, "y" : 61, "img" : "media/img/tree/tree2.png"},
                {"x" : 95, "y" : 84, "img" : "media/img/tree/bush2_g.png"},
                {"x" : 63, "y" : 6, "img" : "media/img/tree/bush3.png"},
                {"x" : 30, "y" : 39, "img" : "media/img/tree/tree1_g_dead.png"},
                {"x" : 32, "y" : 38, "img" : "media/img/tree/tree1_g.png"},
                {"x" : 66, "y" : 67, "img" : "media/img/tree/bush1_g.png"},
                {"x" : 40, "y" : 86, "img" : "media/img/tree/tree1.png"},
                {"x" : 19, "y" : 95, "img" : "media/img/tree/tree3_dead.png"},
                {"x" : 76, "y" : 68, "img" : "media/img/tree/bush4.png"},
                {"x" : 37, "y" : 7, "img" : "media/img/tree/tree1_g.png"},
                {"x" : 99, "y" : 7, "img" : "media/img/tree/bush4.png"},
                {"x" : 87, "y" : 16, "img" : "media/img/tree/tree3_dead.png"},
                {"x" : 5, "y" : 6, "img" : "media/img/tree/bush2_g.png"},
                {"x" : 24, "y" : 40, "img" : "media/img/tree/tree2_g.png"},
                {"x" : 78, "y" : 43, "img" : "media/img/tree/tree2.png"},
                {"x" : 17, "y" : 51, "img" : "media/img/tree/tree3_dead.png"},
                {"x" : 66, "y" : 72, "img" : "media/img/tree/tree1.png"},
                {"x" : 70, "y" : 82, "img" : "media/img/tree/trunk.png"},
                {"x" : 42, "y" : 34, "img" : "media/img/tree/bush1.png"},
                {"x" : 9, "y" : 52, "img" : "media/img/tree/bush2.png"},
                {"x" : 33, "y" : 43, "img" : "media/img/tree/tree1_g.png"},
                {"x" : 85, "y" : 34, "img" : "media/img/tree/tree1_g.png"},
                {"x" : 72, "y" : 23, "img" : "media/img/tree/bush1_g.png"},
                {"x" : 60, "y" : 98, "img" : "media/img/tree/bush2_g.png"},
                {"x" : 75, "y" : 34, "img" : "media/img/tree/tree1_dead.png"},
                {"x" : 54, "y" : 67, "img" : "media/img/tree/tree1_g.png"},
                {"x" : 40, "y" : 48, "img" : "media/img/tree/tree3_dead.png"},
                {"x" : 63, "y" : 23, "img" : "media/img/tree/bush1_g_dead.png"},
                {"x" : 75, "y" : 33, "img" : "media/img/tree/bush3.png"},
                {"x" : 82, "y" : 45, "img" : "media/img/tree/tree1_g_dead.png"},
                {"x" : 30, "y" : 4, "img" : "media/img/tree/bush2.png"},
                {"x" : 89, "y" : 41, "img" : "media/img/tree/tree2_g.png"},
                {"x" : 56, "y" : 93, "img" : "media/img/tree/tree3.png"},
                {"x" : 18, "y" : 49, "img" : "media/img/tree/bush4.png"},
                {"x" : 60, "y" : 64, "img" : "media/img/tree/tree1_g_dead.png"},
                {"x" : 79, "y" : 38, "img" : "media/img/tree/bush4.png"},
                {"x" : 42, "y" : 42, "img" : "media/img/tree/tree1_g.png"},
                {"x" : 68, "y" : 66, "img" : "media/img/tree/tree3.png"},
                {"x" : 25, "y" : 99, "img" : "media/img/tree/bush3.png"},
                {"x" : 94, "y" : 12, "img" : "media/img/tree/bush1_g.png"},
                {"x" : 18, "y" : 73, "img" : "media/img/tree/bush2_g.png"},
                {"x" : 8, "y" : 76, "img" : "media/img/tree/tree2_g.png"},
                {"x" : 14, "y" : 45, "img" : "media/img/tree/tree2.png"},
                {"x" : 16, "y" : 37, "img" : "media/img/tree/bush4.png"},
                {"x" : 0, "y" : 55, "img" : "media/img/tree/bush1_g.png"},
                {"x" : 73, "y" : 31, "img" : "media/img/tree/bush1_g.png"},
                {"x" : 60, "y" : 13, "img" : "media/img/tree/bush2_g.png"},
                {"x" : 73, "y" : 72, "img" : "media/img/tree/bush2_g.png"},
                {"x" : 66, "y" : 97, "img" : "media/img/tree/bush1_g_dead.png"},
                {"x" : 32, "y" : 11, "img" : "media/img/tree/tree1.png"},
                {"x" : 51, "y" : 27, "img" : "media/img/tree/tree1_g.png"},
                {"x" : 21, "y" : 4, "img" : "media/img/tree/bush3.png"},
                {"x" : 68, "y" : 78, "img" : "media/img/tree/tree1_g.png"},
                {"x" : 59, "y" : 49, "img" : "media/img/tree/bush1_g_dead.png"},
                {"x" : 81, "y" : 15, "img" : "media/img/tree/tree1_g_dead.png"},
                {"x" : 9, "y" : 66, "img" : "media/img/tree/bush4.png"},
                {"x" : 0, "y" : 79, "img" : "media/img/tree/bush2.png"},
                {"x" : 23, "y" : 30, "img" : "media/img/tree/bush1_g.png"},
                {"x" : 95, "y" : 94, "img" : "media/img/tree/bush2.png"},
                {"x" : 91, "y" : 73, "img" : "media/img/tree/bush2.png"},
                {"x" : 47, "y" : 43, "img" : "media/img/tree/bush1.png"},
                {"x" : 62, "y" : 83, "img" : "media/img/tree/tree3.png"},
                {"x" : 53, "y" : 50, "img" : "media/img/tree/bush3.png"},
                {"x" : 71, "y" : 23, "img" : "media/img/tree/tree1_dead.png"},
                {"x" : 59, "y" : 3, "img" : "media/img/tree/tree1.png"},
                {"x" : 39, "y" : 18, "img" : "media/img/tree/tree1_g_dead.png"},
                {"x" : 65, "y" : 48, "img" : "media/img/tree/tree1_g_dead.png"},
                {"x" : 35, "y" : 19, "img" : "media/img/tree/bush4.png"},
                {"x" : 63, "y" : 93, "img" : "media/img/tree/tree1_g.png"},
                {"x" : 46, "y" : 52, "img" : "media/img/tree/trunk2.png"},
                {"x" : 89, "y" : 23, "img" : "media/img/tree/tree1_g_dead.png"},
                {"x" : 89, "y" : 58, "img" : "media/img/tree/bush1_g_dead.png"},
                {"x" : 75, "y" : 39, "img" : "media/img/tree/tree1_g_dead.png"},
                {"x" : 84, "y" : 51, "img" : "media/img/tree/trunk2.png"},
                {"x" : 1, "y" : 63, "img" : "media/img/tree/tree2.png"},
                {"x" : 16, "y" : 33, "img" : "media/img/tree/bush1_g_dead.png"},
                {"x" : 84, "y" : 94, "img" : "media/img/tree/tree2.png"},
                {"x" : 51, "y" : 37, "img" : "media/img/tree/tree2.png"},
                {"x" : 27, "y" : 78, "img" : "media/img/tree/tree3.png"},
                {"x" : 41, "y" : 73, "img" : "media/img/tree/bush4.png"},
                {"x" : 5, "y" : 26, "img" : "media/img/tree/tree1.png"},
                {"x" : 10, "y" : 49, "img" : "media/img/tree/bush2_g.png"},
                {"x" : 71, "y" : 81, "img" : "media/img/tree/tree2_g.png"},
                {"x" : 32, "y" : 15, "img" : "media/img/tree/bush1_g_dead.png"},
                {"x" : 53, "y" : 78, "img" : "media/img/tree/trunk2.png"},
                {"x" : 88, "y" : 26, "img" : "media/img/tree/tree2.png"},
                {"x" : 68, "y" : 77, "img" : "media/img/tree/bush1_g_dead.png"},
                {"x" : 40, "y" : 20, "img" : "media/img/tree/tree1.png"},
                {"x" : 84, "y" : 49, "img" : "media/img/tree/bush1_g.png"},
                {"x" : 79, "y" : 77, "img" : "media/img/tree/tree1_g.png"},
                {"x" : 83, "y" : 73, "img" : "media/img/tree/trunk.png"},
                {"x" : 40, "y" : 1, "img" : "media/img/tree/bush1_g.png"},
                {"x" : 48, "y" : 36, "img" : "media/img/tree/bush2.png"},
                {"x" : 56, "y" : 89, "img" : "media/img/tree/tree3_dead.png"},
                {"x" : 83, "y" : 35, "img" : "media/img/tree/tree1_g.png"},
                {"x" : 10, "y" : 51, "img" : "media/img/tree/bush2.png"},
                {"x" : 51, "y" : 70, "img" : "media/img/tree/tree3_dead.png"},
                {"x" : 16, "y" : 28, "img" : "media/img/tree/trunk2.png"},
                {"x" : 28, "y" : 20, "img" : "media/img/tree/tree1_dead.png"},
                {"x" : 54, "y" : 97, "img" : "media/img/tree/trunk.png"},
                {"x" : 12, "y" : 94, "img" : "media/img/tree/tree3_dead.png"},
                {"x" : 64, "y" : 65, "img" : "media/img/tree/bush2_g.png"},
                {"x" : 90, "y" : 79, "img" : "media/img/tree/bush2_g.png"},
                {"x" : 47, "y" : 49, "img" : "media/img/tree/bush2_g.png"},
                {"x" : 31, "y" : 20, "img" : "media/img/tree/tree1_g.png"},
                {"x" : 81, "y" : 36, "img" : "media/img/tree/tree1.png"},
                {"x" : 0, "y" : 35, "img" : "media/img/tree/bush2_g.png"},
                {"x" : 92, "y" : 3, "img" : "media/img/tree/bush1.png"},
                {"x" : 90, "y" : 29, "img" : "media/img/tree/bush3.png"},
                {"x" : 90, "y" : 40, "img" : "media/img/tree/bush3.png"},
                {"x" : 65, "y" : 93, "img" : "media/img/tree/trunk2.png"},
                {"x" : 93, "y" : 3, "img" : "media/img/tree/tree1_g.png"},
                {"x" : 9, "y" : 52, "img" : "media/img/tree/bush1_g.png"},
                {"x" : 32, "y" : 39, "img" : "media/img/tree/tree1_dead.png"},
                {"x" : 77, "y" : 44, "img" : "media/img/tree/bush1.png"},
                {"x" : 85, "y" : 48, "img" : "media/img/tree/bush1.png"},
                {"x" : 83, "y" : 14, "img" : "media/img/tree/bush1_g_dead.png"},
                {"x" : 22, "y" : 83, "img" : "media/img/tree/tree3_dead.png"},
                {"x" : 58, "y" : 41, "img" : "media/img/tree/tree3_dead.png"},
                {"x" : 17, "y" : 89, "img" : "media/img/tree/bush3.png"},
                {"x" : 41, "y" : 98, "img" : "media/img/tree/bush1_g.png"},
                {"x" : 0, "y" : 98, "img" : "media/img/tree/bush1_g_dead.png"},
                {"x" : 15, "y" : 59, "img" : "media/img/tree/bush1.png"},
                {"x" : 55, "y" : 50, "img" : "media/img/tree/tree1_dead.png"},
                {"x" : 66, "y" : 89, "img" : "media/img/tree/trunk2.png"},
                {"x" : 74, "y" : 96, "img" : "media/img/tree/tree1_dead.png"},
                {"x" : 80, "y" : 82, "img" : "media/img/tree/tree3.png"},
                {"x" : 53, "y" : 7, "img" : "media/img/tree/bush2.png"},
                {"x" : 58, "y" : 84, "img" : "media/img/tree/tree3.png"},
                {"x" : 25, "y" : 0, "img" : "media/img/tree/bush1_g_dead.png"},
                {"x" : 80, "y" : 64, "img" : "media/img/tree/bush2_g.png"},
                {"x" : 91, "y" : 58, "img" : "media/img/tree/tree3.png"},
                {"x" : 17, "y" : 21, "img" : "media/img/tree/bush1_g.png"},
                {"x" : 29, "y" : 75, "img" : "media/img/tree/tree2_g.png"},
                {"x" : 1, "y" : 82, "img" : "media/img/tree/bush2.png"},
                {"x" : 39, "y" : 48, "img" : "media/img/tree/trunk.png"},
                {"x" : 49, "y" : 3, "img" : "media/img/tree/tree3_dead.png"},
                {"x" : 54, "y" : 14, "img" : "media/img/tree/tree1_g.png"},
                {"x" : 20, "y" : 81, "img" : "media/img/tree/tree1.png"},
                {"x" : 10, "y" : 19, "img" : "media/img/tree/bush1_g.png"},
                {"x" : 26, "y" : 27, "img" : "media/img/tree/bush1_g.png"},
                {"x" : 97, "y" : 38, "img" : "media/img/tree/bush3.png"},
                {"x" : 94, "y" : 69, "img" : "media/img/tree/trunk.png"},
                {"x" : 10, "y" : 97, "img" : "media/img/tree/tree1_g_dead.png"},
                {"x" : 11, "y" : 1, "img" : "media/img/tree/tree1_g_dead.png"},
                {"x" : 2, "y" : 50, "img" : "media/img/tree/trunk2.png"},
                {"x" : 17, "y" : 24, "img" : "media/img/tree/tree1.png"},
                {"x" : 81, "y" : 57, "img" : "media/img/tree/tree3_dead.png"},
                {"x" : 52, "y" : 90, "img" : "media/img/tree/tree1_dead.png"},
                {"x" : 48, "y" : 83, "img" : "media/img/tree/bush1_g_dead.png"},
                {"x" : 61, "y" : 5, "img" : "media/img/tree/tree2_g.png"},
                {"x" : 80, "y" : 38, "img" : "media/img/tree/tree1_g_dead.png"},
                {"x" : 68, "y" : 11, "img" : "media/img/tree/tree1.png"},
                {"x" : 85, "y" : 40, "img" : "media/img/tree/tree1_g.png"},
                {"x" : 16, "y" : 88, "img" : "media/img/tree/bush1_g.png"},
                {"x" : 34, "y" : 30, "img" : "media/img/tree/bush4.png"},
                {"x" : 11, "y" : 1, "img" : "media/img/tree/tree2_g.png"},
                {"x" : 57, "y" : 11, "img" : "media/img/tree/trunk.png"},
                {"x" : 42, "y" : 13, "img" : "media/img/tree/tree1_g.png"},
                {"x" : 19, "y" : 88, "img" : "media/img/tree/tree2.png"},
                {"x" : 75, "y" : 37, "img" : "media/img/tree/bush2_g.png"},
                {"x" : 66, "y" : 30, "img" : "media/img/tree/tree2.png"},
                {"x" : 91, "y" : 48, "img" : "media/img/tree/tree2.png"},
                {"x" : 18, "y" : 53, "img" : "media/img/tree/bush2_g.png"},
                {"x" : 23, "y" : 18, "img" : "media/img/tree/tree3_dead.png"},
                {"x" : 5, "y" : 60, "img" : "media/img/tree/bush4.png"},
                {"x" : 62, "y" : 41, "img" : "media/img/tree/bush1.png"},
                {"x" : 87, "y" : 77, "img" : "media/img/tree/bush1.png"},
                {"x" : 42, "y" : 74, "img" : "media/img/tree/bush1.png"},
                {"x" : 40, "y" : 38, "img" : "media/img/tree/tree3.png"},
                {"x" : 48, "y" : 66, "img" : "media/img/tree/bush2_g.png"},
                {"x" : 71, "y" : 0, "img" : "media/img/tree/bush2.png"},
                {"x" : 74, "y" : 35, "img" : "media/img/tree/bush4.png"},
                {"x" : 59, "y" : 39, "img" : "media/img/tree/bush4.png"},
                {"x" : 14, "y" : 5, "img" : "media/img/tree/bush1.png"},
                {"x" : 46, "y" : 1, "img" : "media/img/tree/trunk.png"},
                {"x" : 23, "y" : 73, "img" : "media/img/tree/bush1_g_dead.png"},
                {"x" : 71, "y" : 42, "img" : "media/img/tree/tree2.png"},
                {"x" : 47, "y" : 89, "img" : "media/img/tree/tree1_dead.png"},
                {"x" : 5, "y" : 6, "img" : "media/img/tree/tree2_g.png"},
                {"x" : 26, "y" : 9, "img" : "media/img/tree/tree2.png"},
                {"x" : 8, "y" : 92, "img" : "media/img/tree/tree1.png"},
                {"x" : 20, "y" : 95, "img" : "media/img/tree/bush1_g_dead.png"},
                {"x" : 16, "y" : 5, "img" : "media/img/tree/bush1_g.png"},
                {"x" : 16, "y" : 43, "img" : "media/img/tree/trunk2.png"},
                {"x" : 95, "y" : 38, "img" : "media/img/tree/tree3_dead.png"},
                {"x" : 50, "y" : 41, "img" : "media/img/tree/tree3.png"},
                {"x" : 89, "y" : 84, "img" : "media/img/tree/trunk.png"},
                {"x" : 28, "y" : 46, "img" : "media/img/tree/trunk2.png"},
                {"x" : 64, "y" : 65, "img" : "media/img/tree/bush4.png"},
                {"x" : 32, "y" : 91, "img" : "media/img/tree/tree1.png"},
                {"x" : 97, "y" : 58, "img" : "media/img/tree/tree2_g.png"},
                {"x" : 94, "y" : 5, "img" : "media/img/tree/tree1_g_dead.png"},
                {"x" : 39, "y" : 93, "img" : "media/img/tree/bush1_g_dead.png"},
                {"x" : 18, "y" : 94, "img" : "media/img/tree/trunk.png"},
                {"x" : 19, "y" : 91, "img" : "media/img/tree/tree1_g.png"},
                {"x" : 36, "y" : 59, "img" : "media/img/tree/trunk.png"},
                {"x" : 7, "y" : 2, "img" : "media/img/tree/tree1_g_dead.png"},
                {"x" : 25, "y" : 27, "img" : "media/img/tree/bush2_g.png"},
                {"x" : 34, "y" : 98, "img" : "media/img/tree/trunk2.png"},
                {"x" : 60, "y" : 64, "img" : "media/img/tree/tree2_g.png"},
                {"x" : 46, "y" : 86, "img" : "media/img/tree/bush4.png"},
                {"x" : 26, "y" : 48, "img" : "media/img/tree/tree2_g.png"},
                {"x" : 56, "y" : 76, "img" : "media/img/tree/tree2.png"},
                {"x" : 56, "y" : 93, "img" : "media/img/tree/bush1_g_dead.png"},
                {"x" : 63, "y" : 63, "img" : "media/img/tree/trunk.png"},
                {"x" : 48, "y" : 11, "img" : "media/img/tree/bush1_g_dead.png"},
                {"x" : 25, "y" : 23, "img" : "media/img/tree/tree3_dead.png"},
                {"x" : 49, "y" : 69, "img" : "media/img/tree/tree3_dead.png"},
                {"x" : 55, "y" : 31, "img" : "media/img/tree/tree1.png"},
                {"x" : 33, "y" : 32, "img" : "media/img/tree/tree3.png"},
                {"x" : 79, "y" : 8, "img" : "media/img/tree/tree3.png"},
                {"x" : 29, "y" : 49, "img" : "media/img/tree/bush1_g.png"},
                {"x" : 66, "y" : 34, "img" : "media/img/tree/tree1_g.png"},
                {"x" : 18, "y" : 15, "img" : "media/img/tree/tree1_dead.png"},
                {"x" : 73, "y" : 60, "img" : "media/img/tree/tree3_dead.png"},
                {"x" : 32, "y" : 61, "img" : "media/img/tree/tree3.png"},
                {"x" : 81, "y" : 8, "img" : "media/img/tree/trunk2.png"},
                {"x" : 18, "y" : 40, "img" : "media/img/tree/bush2_g.png"},
                {"x" : 77, "y" : 39, "img" : "media/img/tree/bush3.png"},
                {"x" : 55, "y" : 40, "img" : "media/img/tree/trunk.png"},
                {"x" : 74, "y" : 51, "img" : "media/img/tree/bush1_g.png"},
                {"x" : 98, "y" : 59, "img" : "media/img/tree/bush1_g_dead.png"},
                {"x" : 93, "y" : 2, "img" : "media/img/tree/tree2.png"},
                {"x" : 51, "y" : 68, "img" : "media/img/tree/tree1_g.png"},
                {"x" : 87, "y" : 26, "img" : "media/img/tree/bush4.png"},
                {"x" : 86, "y" : 4, "img" : "media/img/tree/tree1_g.png"},
                {"x" : 10, "y" : 54, "img" : "media/img/tree/bush1_g_dead.png"},
                {"x" : 59, "y" : 18, "img" : "media/img/tree/tree1_dead.png"},
                {"x" : 75, "y" : 27, "img" : "media/img/tree/bush1_g_dead.png"},
                {"x" : 31, "y" : 81, "img" : "media/img/tree/bush2_g.png"},
                {"x" : 42, "y" : 74, "img" : "media/img/tree/trunk2.png"},
                {"x" : 1, "y" : 49, "img" : "media/img/tree/trunk.png"},
                {"x" : 42, "y" : 61, "img" : "media/img/tree/trunk.png"},
                {"x" : 52, "y" : 24, "img" : "media/img/tree/tree1_g_dead.png"},
                {"x" : 78, "y" : 82, "img" : "media/img/tree/tree1.png"},
                {"x" : 91, "y" : 49, "img" : "media/img/tree/bush1_g.png"},
                {"x" : 35, "y" : 96, "img" : "media/img/tree/bush2_g.png"},
                {"x" : 27, "y" : 49, "img" : "media/img/tree/bush2.png"},
                {"x" : 48, "y" : 19, "img" : "media/img/tree/bush2_g.png"},
                {"x" : 13, "y" : 55, "img" : "media/img/tree/tree1_g.png"},
                {"x" : 92, "y" : 1, "img" : "media/img/tree/tree1_g_dead.png"},
                {"x" : 5, "y" : 28, "img" : "media/img/tree/bush3.png"},
                {"x" : 84, "y" : 36, "img" : "media/img/tree/tree1_g_dead.png"},
                {"x" : 70, "y" : 65, "img" : "media/img/tree/tree2_g.png"},
                {"x" : 94, "y" : 50, "img" : "media/img/tree/bush4.png"},
                {"x" : 53, "y" : 20, "img" : "media/img/tree/bush2_g.png"},
                {"x" : 52, "y" : 49, "img" : "media/img/tree/bush1_g_dead.png"},
                {"x" : 19, "y" : 60, "img" : "media/img/tree/bush1_g_dead.png"},
                {"x" : 20, "y" : 76, "img" : "media/img/tree/bush1_g.png"},
                {"x" : 98, "y" : 62, "img" : "media/img/tree/bush1.png"},
                {"x" : 2, "y" : 35, "img" : "media/img/tree/bush3.png"},
                {"x" : 68, "y" : 41, "img" : "media/img/tree/tree1_g.png"},
                {"x" : 99, "y" : 52, "img" : "media/img/tree/bush1_g.png"},
                {"x" : 8, "y" : 44, "img" : "media/img/tree/tree2_g.png"},
                {"x" : 93, "y" : 29, "img" : "media/img/tree/bush1.png"},
                {"x" : 43, "y" : 6, "img" : "media/img/tree/bush2_g.png"},
                {"x" : 51, "y" : 3, "img" : "media/img/tree/tree2.png"},
                {"x" : 22, "y" : 45, "img" : "media/img/tree/bush2_g.png"},
                {"x" : 80, "y" : 14, "img" : "media/img/tree/bush1.png"},
                {"x" : 38, "y" : 28, "img" : "media/img/tree/bush4.png"},
                {"x" : 30, "y" : 75, "img" : "media/img/tree/trunk.png"},
                {"x" : 60, "y" : 26, "img" : "media/img/tree/tree3.png"},
                {"x" : 3, "y" : 12, "img" : "media/img/tree/tree2_g.png"},
                {"x" : 65, "y" : 23, "img" : "media/img/tree/bush1_g_dead.png"},
                {"x" : 26, "y" : 46, "img" : "media/img/tree/bush2.png"},
                {"x" : 51, "y" : 19, "img" : "media/img/tree/bush1_g_dead.png"},
                {"x" : 58, "y" : 94, "img" : "media/img/tree/tree3.png"},
                {"x" : 14, "y" : 47, "img" : "media/img/tree/tree2_g.png"},
                {"x" : 93, "y" : 5, "img" : "media/img/tree/tree1_dead.png"},
                {"x" : 83, "y" : 11, "img" : "media/img/tree/tree2_g.png"},
                {"x" : 2, "y" : 67, "img" : "media/img/tree/bush4.png"},
                {"x" : 91, "y" : 54, "img" : "media/img/tree/bush2.png"},
                {"x" : 97, "y" : 18, "img" : "media/img/tree/tree1_g.png"},
                {"x" : 81, "y" : 34, "img" : "media/img/tree/bush1_g_dead.png"},
                {"x" : 88, "y" : 99, "img" : "media/img/tree/bush1_g_dead.png"},
                {"x" : 51, "y" : 26, "img" : "media/img/tree/bush2_g.png"},
                {"x" : 43, "y" : 62, "img" : "media/img/tree/bush2.png"},
                {"x" : 91, "y" : 62, "img" : "media/img/tree/tree2_g.png"},
                {"x" : 74, "y" : 19, "img" : "media/img/tree/bush1_g.png"},
                {"x" : 11, "y" : 79, "img" : "media/img/tree/tree2_g.png"},
                {"x" : 71, "y" : 56, "img" : "media/img/tree/tree1.png"},
                {"x" : 39, "y" : 55, "img" : "media/img/tree/tree1_g_dead.png"},
                {"x" : 85, "y" : 4, "img" : "media/img/tree/bush1_g.png"},
                {"x" : 0, "y" : 78, "img" : "media/img/tree/bush4.png"},
                {"x" : 27, "y" : 8, "img" : "media/img/tree/tree1_g.png"},
                {"x" : 1, "y" : 53, "img" : "media/img/tree/trunk2.png"},
                {"x" : 45, "y" : 48, "img" : "media/img/tree/tree3.png"},
                {"x" : 71, "y" : 10, "img" : "media/img/tree/bush2_g.png"},
                {"x" : 29, "y" : 1, "img" : "media/img/tree/bush2_g.png"},
                {"x" : 62, "y" : 76, "img" : "media/img/tree/bush1_g.png"},
                {"x" : 33, "y" : 38, "img" : "media/img/tree/tree3.png"},
                {"x" : 25, "y" : 40, "img" : "media/img/tree/tree3.png"},
                {"x" : 55, "y" : 89, "img" : "media/img/tree/tree3_dead.png"},
                {"x" : 21, "y" : 49, "img" : "media/img/tree/bush4.png"},
                {"x" : 46, "y" : 50, "img" : "media/img/tree/bush2.png"},
                {"x" : 55, "y" : 53, "img" : "media/img/tree/tree3.png"},
                {"x" : 35, "y" : 66, "img" : "media/img/tree/tree1_g.png"},
                {"x" : 22, "y" : 41, "img" : "media/img/tree/bush2_g.png"},
                {"x" : 36, "y" : 97, "img" : "media/img/tree/tree1_dead.png"},
                {"x" : 7, "y" : 69, "img" : "media/img/tree/bush1.png"},
                {"x" : 58, "y" : 4, "img" : "media/img/tree/trunk2.png"},
                {"x" : 14, "y" : 82, "img" : "media/img/tree/bush1_g.png"},
                {"x" : 60, "y" : 0, "img" : "media/img/tree/tree1_g_dead.png"},
                {"x" : 17, "y" : 92, "img" : "media/img/tree/tree3.png"},
                {"x" : 16, "y" : 82, "img" : "media/img/tree/trunk2.png"},
                {"x" : 38, "y" : 25, "img" : "media/img/tree/bush1_g_dead.png"},
                {"x" : 97, "y" : 7, "img" : "media/img/tree/tree3.png"},
                {"x" : 60, "y" : 17, "img" : "media/img/tree/tree3.png"},
                {"x" : 90, "y" : 95, "img" : "media/img/tree/trunk2.png"},
                {"x" : 4, "y" : 99, "img" : "media/img/tree/tree3_dead.png"},
                {"x" : 5, "y" : 35, "img" : "media/img/tree/tree3_dead.png"}
            ]
        }
    ]
}
